Metadata-Version: 2.1
Name: odoo12-addon-l10n-it-pos-fatturapa
Version: 12.0.1.0.2
Summary: Gestione dati fattura elettronica del cliente all'interno dell'interfaccia del POS
Home-page: https://github.com/OCA/l10n-italy
Author: Roberto Fichera, Odoo Community Association (OCA)
Author-email: support@odoo-community.org
License: AGPL-3
Platform: UNKNOWN
Classifier: Programming Language :: Python
Classifier: Framework :: Odoo
Classifier: License :: OSI Approved :: GNU Affero General Public License v3
Classifier: Development Status :: 4 - Beta
Requires-Python: >=3.5
Requires-Dist: odoo12-addon-l10n-it-fatturapa
Requires-Dist: odoo12-addon-l10n-it-pos-fiscalcode
Requires-Dist: odoo12-addon-pos-partner-firstname
Requires-Dist: odoo (<12.1dev,>=12.0a)
